connection_to_mongodb/__init__.py
connection_to_mongodb/manager.py
connection_to_mongodb/mongoModels.py
mongo_model_base/__init__.py
mongo_model_base/mongoModels.py
django_connect_mongo-1.14.0.dist-info/METADATA
django_connect_mongo-1.14.0.dist-info/WHEEL
django_connect_mongo-1.14.0.dist-info/top_level.txt
django_connect_mongo-1.14.0.dist-info/RECORD
