Metadata-Version: 2.1
Name: django-connect-mongo
Version: 1.14.0
Summary: we use this package to work with mongodb easier
Home-page: UNKNOWN
Author: hieucao192
Author-email: hieucaohd@gmail.com
License: MIT
Platform: UNKNOWN
Classifier: License :: OSI Approved :: MIT License
Classifier: Programming Language :: Python :: 3
Classifier: Programming Language :: Python :: 3.9
Requires-Dist: pymongo[srv]
